salgo/__init__.py
salgo/data.csv
salgo/data_loader.py
salgo/trainer.py
salgo-0.2.dist-info/METADATA
salgo-0.2.dist-info/WHEEL
salgo-0.2.dist-info/top_level.txt
salgo-0.2.dist-info/RECORD
