Metadata-Version: 2.1
Name: salgo
Version: 0.2
Summary: A package for S algorithm implementation with datasets included.
Home-page: UNKNOWN
Author: Raghul
Author-email: raghulares@gmail.com
License: UNKNOWN
Platform: UNKNOWN
Requires-Dist: pandas
Requires-Dist: numpy
